{
    "uuid": [
        {
            "value": "9ebb9805-59c1-4186-b0c7-9d1240c26b14"
        }
    ],
    "langcode": [
        {
            "value": "en"
        }
    ],
    "bundle": [
        {
            "target_id": "image",
            "target_type": "media_type",
            "target_uuid": "b17d1dd2-b562-4656-b080-3f9bec3625f6"
        }
    ],
    "revision_created": [
        {
            "value": "2022-07-18T13:17:09+00:00",
            "format": "Y-m-d\\TH:i:sP"
        }
    ],
    "revision_user": [
        {
            "target_type": "user",
            "target_uuid": "4c5767f6-fd4e-4d0f-9130-989c9eb98547"
        }
    ],
    "revision_log_message": [],
    "status": [
        {
            "value": true
        }
    ],
    "uid": [
        {
            "target_type": "user",
            "target_uuid": "4c5767f6-fd4e-4d0f-9130-989c9eb98547"
        }
    ],
    "name": [
        {
            "value": "gs_banner3.png"
        }
    ],
    "thumbnail": [
        {
            "alt": "background image - student watching video",
            "title": null,
            "width": 1280,
            "height": 427,
            "target_type": "file",
            "target_uuid": "65616fe3-7737-4807-9cd5-f1d5dfedcba2"
        }
    ],
    "created": [
        {
            "value": "2022-07-18T13:16:54+00:00",
            "format": "Y-m-d\\TH:i:sP"
        }
    ],
    "changed": [
        {
            "value": "2022-07-18T13:17:09+00:00",
            "format": "Y-m-d\\TH:i:sP"
        }
    ],
    "default_langcode": [
        {
            "value": true
        }
    ],
    "revision_translation_affected": [
        {
            "value": true
        }
    ],
    "path": [
        {
            "alias": null,
            "pid": null,
            "langcode": "en"
        }
    ],
    "field_media_image": [
        {
            "alt": "background image - student watching video",
            "title": "",
            "width": 1280,
            "height": 427,
            "target_type": "file",
            "target_uuid": "65616fe3-7737-4807-9cd5-f1d5dfedcba2"
        }
    ]
}