{
    "uuid": [
        {
            "value": "93d975a0-e8ab-4b5d-9af1-b63915361bbc"
        }
    ],
    "langcode": [
        {
            "value": "en"
        }
    ],
    "bundle": [
        {
            "value": "menu_link_content"
        }
    ],
    "revision_created": [
        {
            "value": "2022-07-18T01:46:20+00:00",
            "format": "Y-m-d\\TH:i:sP"
        }
    ],
    "revision_user": [],
    "revision_log_message": [],
    "enabled": [
        {
            "value": true
        }
    ],
    "title": [
        {
            "value": "Digital Library Center"
        }
    ],
    "description": [],
    "menu_name": [
        {
            "value": "collections"
        }
    ],
    "link": [
        {
            "uri": "internal:\/special-collections\/digital-library-center",
            "title": "",
            "options": []
        }
    ],
    "external": [
        {
            "value": false
        }
    ],
    "rediscover": [
        {
            "value": true
        }
    ],
    "weight": [
        {
            "value": -47
        }
    ],
    "expanded": [
        {
            "value": false
        }
    ],
    "parent": [],
    "changed": [
        {
            "value": "2022-07-18T01:47:38+00:00",
            "format": "Y-m-d\\TH:i:sP"
        }
    ],
    "default_langcode": [
        {
            "value": true
        }
    ],
    "revision_translation_affected": [
        {
            "value": true
        }
    ]
}