{
    "uuid": [
        {
            "value": "dd6bea59-0ffb-4397-a977-b750a63eccb9"
        }
    ],
    "langcode": [
        {
            "value": "und"
        }
    ],
    "path": [
        {
            "value": "\/webform\/interlibrary_loan_account_assist\/submissions"
        }
    ],
    "alias": [
        {
            "value": "\/find-and-borrow\/extended-borrowing\/ill-account-assistance-form\/submissions"
        }
    ],
    "status": [
        {
            "value": true
        }
    ]
}