{
    "uuid": [
        {
            "value": "598492bb-cd8a-415b-ae30-55efca8572c1"
        }
    ],
    "langcode": [
        {
            "value": "en"
        }
    ],
    "vid": [
        {
            "target_id": "study_space_type",
            "target_type": "taxonomy_vocabulary",
            "target_uuid": "b9a64e96-d06a-4e95-a8a9-5960f56fbee2"
        }
    ],
    "revision_created": [
        {
            "value": "2022-06-10T16:44:13+00:00",
            "format": "Y-m-d\\TH:i:sP"
        }
    ],
    "revision_user": [],
    "revision_log_message": [],
    "status": [
        {
            "value": true
        }
    ],
    "name": [
        {
            "value": "Graduate Use"
        }
    ],
    "description": [
        {
            "value": null,
            "format": null
        }
    ],
    "weight": [
        {
            "value": 2
        }
    ],
    "parent": [
        {
            "target_id": null
        }
    ],
    "changed": [
        {
            "value": "2022-07-14T15:40:30+00:00",
            "format": "Y-m-d\\TH:i:sP"
        }
    ],
    "default_langcode": [
        {
            "value": true
        }
    ],
    "revision_translation_affected": [
        {
            "value": true
        }
    ],
    "path": [
        {
            "alias": null,
            "pid": null,
            "langcode": "en"
        }
    ]
}